osism/__init__.py
osism/__main__.py
osism/api.py
osism/main.py
osism/settings.py
osism/commands/__init__.py
osism/commands/amphora.py
osism/commands/apply.py
osism/commands/baremetal.py
osism/commands/check.py
osism/commands/compose.py
osism/commands/compute.py
osism/commands/configuration.py
osism/commands/console.py
osism/commands/container.py
osism/commands/get.py
osism/commands/loadbalancer.py
osism/commands/lock.py
osism/commands/log.py
osism/commands/manage.py
osism/commands/migrate.py
osism/commands/netbox.py
osism/commands/noset.py
osism/commands/octavia.py
osism/commands/reconciler.py
osism/commands/redfish.py
osism/commands/server.py
osism/commands/service.py
osism/commands/set.py
osism/commands/sonic.py
osism/commands/status.py
osism/commands/stress.py
osism/commands/sync.py
osism/commands/task.py
osism/commands/validate.py
osism/commands/vault.py
osism/commands/volume.py
osism/commands/wait.py
osism/commands/worker.py
osism/data/__init__.py
osism/data/enums.py
osism/data/playbooks.py
osism/services/__init__.py
osism/services/event_bridge.py
osism/services/listener.py
osism/services/websocket_manager.py
osism/tasks/__init__.py
osism/tasks/ansible.py
osism/tasks/ceph.py
osism/tasks/conductor.py
osism/tasks/kolla.py
osism/tasks/kubernetes.py
osism/tasks/netbox.py
osism/tasks/openstack.py
osism/tasks/reconciler.py
osism/tasks/conductor/__init__.py
osism/tasks/conductor/config.py
osism/tasks/conductor/ironic.py
osism/tasks/conductor/netbox.py
osism/tasks/conductor/redfish.py
osism/tasks/conductor/utils.py
osism/tasks/conductor/sonic/__init__.py
osism/tasks/conductor/sonic/bgp.py
osism/tasks/conductor/sonic/cache.py
osism/tasks/conductor/sonic/config_generator.py
osism/tasks/conductor/sonic/connections.py
osism/tasks/conductor/sonic/constants.py
osism/tasks/conductor/sonic/device.py
osism/tasks/conductor/sonic/exporter.py
osism/tasks/conductor/sonic/interface.py
osism/tasks/conductor/sonic/sync.py
osism/utils/__init__.py
osism/utils/rabbitmq.py
osism-0.20260129.1.dist-info/licenses/AUTHORS
osism-0.20260129.1.dist-info/licenses/LICENSE
osism-0.20260129.1.dist-info/METADATA
osism-0.20260129.1.dist-info/WHEEL
osism-0.20260129.1.dist-info/entry_points.txt
osism-0.20260129.1.dist-info/pbr.json
osism-0.20260129.1.dist-info/top_level.txt
osism-0.20260129.1.dist-info/RECORD
