Metadata-Version: 2.4
Name: osism
Version: 0.20260129.1
Summary: OSISM manager interface
Home-page: https://github.com/osism/python-osism
Author: OSISM GmbH
Author-email: info@osism.tech
Classifier: Development Status :: 5 - Production/Stable
Classifier: Environment :: Console
Classifier: Intended Audience :: Developers
Classifier: Intended Audience :: Information Technology
Classifier: License :: OSI Approved :: Apache Software License
Classifier: Operating System :: OS Independent
Classifier: Programming Language :: Python
Classifier: Programming Language :: Python :: 3 :: Only
Classifier: Programming Language :: Python :: 3
Classifier: Programming Language :: Python :: 3.8
Classifier: Programming Language :: Python :: 3.9
Classifier: Programming Language :: Python :: 3.10
Classifier: Programming Language :: Python :: 3.11
Requires-Python: >=3.8
License-File: LICENSE
License-File: AUTHORS
Requires-Dist: ClusterShell==1.9.3
Requires-Dist: GitPython==3.1.46
Requires-Dist: Jinja2==3.1.6
Requires-Dist: PyMySQL==1.1.2
Requires-Dist: PyYAML==6.0.3
Requires-Dist: ara==1.7.3
Requires-Dist: celery[redis]==5.6.2
Requires-Dist: cliff==4.13.1
Requires-Dist: deepdiff==8.6.1
Requires-Dist: docker==7.1.0
Requires-Dist: dtrack-auditor==1.5.0
Requires-Dist: fastapi==0.128.0
Requires-Dist: flower==2.0.1
Requires-Dist: hiredis==3.3.0
Requires-Dist: jc==1.25.6
Requires-Dist: keystoneauth1==5.13.0
Requires-Dist: kombu==5.6.2
Requires-Dist: kubernetes==33.1.0
Requires-Dist: loguru==0.7.3
Requires-Dist: nbcli==0.10.0.dev2
Requires-Dist: openstacksdk==4.9.0
Requires-Dist: paramiko==4.0.0
Requires-Dist: pottery==3.0.1
Requires-Dist: prompt-toolkit==3.0.52
Requires-Dist: pyang==2.7.1
Requires-Dist: pynetbox==7.6.1
Requires-Dist: pytest-testinfra==10.2.2
Requires-Dist: python-dateutil==2.9.0.post0
Requires-Dist: redfish==3.3.4
Requires-Dist: setuptools==80.10.2
Requires-Dist: sqlmodel==0.0.31
Requires-Dist: sushy==5.9.0
Requires-Dist: tabulate==0.9.0
Requires-Dist: transitions==0.9.3
Requires-Dist: uvicorn[standard]==0.40.0
Requires-Dist: validators==0.35.0
Requires-Dist: watchdog==6.0.0
Requires-Dist: websockets==16.0
Provides-Extra: ansible
Requires-Dist: ansible-runner==2.4.2; extra == "ansible"
Requires-Dist: ansible-core==2.19.3; extra == "ansible"
Provides-Extra: openstack-image-manager
Requires-Dist: openstack-image-manager==0.20260128.0; extra == "openstack-image-manager"
Dynamic: author
Dynamic: author-email
Dynamic: classifier
Dynamic: home-page
Dynamic: license-file
Dynamic: requires-dist
Dynamic: requires-python
Dynamic: summary
